vecquery_tune/__init__.py
vecquery_tune/create_database.py
vecquery_tune/custom_embedding.py
vecquery_tune/fine_tune.py
vecquery_tune/inference.py
vecquery_tune/loss_funcs.py
vecquery_tune/model.py
vecquery_tune/test.py
vecquery_tune/vecquery_tune.py
vecquery_tune-0.0.7.dist-info/LICENSE
vecquery_tune-0.0.7.dist-info/METADATA
vecquery_tune-0.0.7.dist-info/WHEEL
vecquery_tune-0.0.7.dist-info/top_level.txt
vecquery_tune-0.0.7.dist-info/RECORD
