Metadata-Version: 2.1
Name: vecquery-tune
Version: 0.0.7
Summary: Fine-tune BERT for vectorized query search
Home-page: https://github.com/afurkank/vecquery_tune
Author: Ahmet Furkan Karacık
Author-email: furkan.karacikq@gmail.com
License: MIT
License-File: LICENSE
Requires-Dist: transformers (>=4.31.0)
Requires-Dist: torch (>=2.0.1)
Requires-Dist: chromadb (>=0.4.5)
Requires-Dist: peft (>=0.5.0)
